browserforge/__main__.py
browserforge/bayesian_network.py
browserforge/download.py
browserforge/fingerprints/__init__.py
browserforge/fingerprints/data/__init__.py
browserforge/fingerprints/generator.py
browserforge/headers/__init__.py
browserforge/headers/data/__init__.py
browserforge/headers/generator.py
browserforge/headers/utils.py
browserforge/injectors/__init__.py
browserforge/injectors/data/__init__.py
browserforge/injectors/data/utils.js.xz
browserforge/injectors/playwright/__init__.py
browserforge/injectors/playwright/injector.py
browserforge/injectors/pyppeteer/__init__.py
browserforge/injectors/pyppeteer/injector.py
browserforge/injectors/undetected_playwright/__init__.py
browserforge/injectors/undetected_playwright/injector.py
browserforge/injectors/utils.py
browserforge/py.typed
browserforge-1.2.1.dist-info/LICENSE
browserforge-1.2.1.dist-info/METADATA
browserforge-1.2.1.dist-info/WHEEL
browserforge-1.2.1.dist-info/RECORD
